odoo/addons/stock_move_responsible/README.rst
odoo/addons/stock_move_responsible/__init__.py
odoo/addons/stock_move_responsible/__manifest__.py
odoo/addons/stock_move_responsible/i18n/es.po
odoo/addons/stock_move_responsible/models/__init__.py
odoo/addons/stock_move_responsible/models/stock_move.py
odoo/addons/stock_move_responsible/readme/CONTRIBUTORS.md
odoo/addons/stock_move_responsible/readme/DESCRIPTION.md
odoo/addons/stock_move_responsible/readme/USAGE.md
odoo/addons/stock_move_responsible/static/description/icon.png
odoo/addons/stock_move_responsible/static/description/index.html
odoo/addons/stock_move_responsible/views/stock_move_views.xml
odoo_addon_stock_move_responsible-17.0.1.0.0.2.dist-info/METADATA
odoo_addon_stock_move_responsible-17.0.1.0.0.2.dist-info/WHEEL
odoo_addon_stock_move_responsible-17.0.1.0.0.2.dist-info/top_level.txt
odoo_addon_stock_move_responsible-17.0.1.0.0.2.dist-info/RECORD
